ardot_permit_officer/__init__.py
ardot_permit_officer/cli.py
ardot_permit_officer/scraper.py
ardot_permit_officer-1.0.1.dist-info/licenses/LICENSE
ardot_permit_officer-1.0.1.dist-info/METADATA
ardot_permit_officer-1.0.1.dist-info/WHEEL
ardot_permit_officer-1.0.1.dist-info/entry_points.txt
ardot_permit_officer-1.0.1.dist-info/top_level.txt
ardot_permit_officer-1.0.1.dist-info/RECORD
