Metadata-Version: 2.4
Name: ardot_permit_officer
Version: 1.0.1
Summary: Fetch ARDOT permit officer contact info from all 10 district pages.
Home-page: https://github.com/yourusername/ardot_permit_officer
Author: Your Name
Author-email: Justin Kumpe <jakumpe@kumpeapps.com>
License: MIT
Classifier: Programming Language :: Python :: 3
Classifier: License :: OSI Approved :: MIT License
Classifier: Operating System :: OS Independent
Requires-Python: >=3.7
License-File: LICENSE
Requires-Dist: requests
Requires-Dist: beautifulsoup4
Dynamic: author
Dynamic: home-page
Dynamic: license-file
Dynamic: requires-python
